fast_gpu_voronoi/__init__.py
fast_gpu_voronoi/__research.py
fast_gpu_voronoi/__version__.py
fast_gpu_voronoi/debug.py
fast_gpu_voronoi/jfa.py
fast_gpu_voronoi/utils.py
fast_gpu_voronoi/cl/brute.cl
fast_gpu_voronoi/cl/jfa.cl
fast_gpu_voronoi/cl/jfa_circle.cl
fast_gpu_voronoi/cl/jfa_regular.cl
fast_gpu_voronoi/cl/jfa_star.cl
fast_gpu_voronoi/cl/noise.cl
fast_gpu_voronoi-0.0.3.dist-info/LICENSE
fast_gpu_voronoi-0.0.3.dist-info/METADATA
fast_gpu_voronoi-0.0.3.dist-info/WHEEL
fast_gpu_voronoi-0.0.3.dist-info/top_level.txt
fast_gpu_voronoi-0.0.3.dist-info/RECORD
