Metadata-Version: 2.1
Name: fast-gpu-voronoi
Version: 0.0.3
Summary: GPU-Accelerated Jump Flooding Algorithm for Voronoi Diagram in log*(n)
Home-page: https://github.com/maciejczyzewski/fast_gpu_voronoi
Author: Maciej A. Czyzewski
Author-email: maciejanthonyczyzewski@gmail.com
License: MIT
Platform: UNKNOWN
Classifier: License :: OSI Approved :: MIT License
Classifier: Programming Language :: Python
Classifier: Programming Language :: Python :: 3
Classifier: Programming Language :: Python :: 3.6
Classifier: Programming Language :: Python :: Implementation :: CPython
Classifier: Programming Language :: Python :: Implementation :: PyPy
Requires-Python: >=3.1.0
Requires-Dist: imageio (==2.4.1)
Requires-Dist: matplotlib (==3.0.3)
Requires-Dist: pyopencl (==2018.2.5)
Requires-Dist: numpy (==1.16.2)
Requires-Dist: tqdm (==4.28.1)
